py21/__init__.py
py21/card.py
py21/cli.py
py21/conftest.py
py21/deck.py
py21/game.py
py21/hand.py
py21/player.py
py21/rules.json
py21/strategies.py
py21/utils.py
py21/strategy_files/basic_hard.csv
py21/strategy_files/basic_soft.csv
py21/strategy_files/basic_split.csv
py21-1.6.0.dist-info/LICENSE
py21-1.6.0.dist-info/METADATA
py21-1.6.0.dist-info/WHEEL
py21-1.6.0.dist-info/entry_points.txt
py21-1.6.0.dist-info/top_level.txt
py21-1.6.0.dist-info/RECORD
