Metadata-Version: 2.1
Name: py21
Version: 1.6.0
Summary: Library for running blackjack simulations
Home-page: https://github.com/andersonfrailey/blackjack
Author: Anderson Frailey
Author-email: andersonfrailey@gmail.org
License: UNKNOWN
Platform: UNKNOWN
Classifier: Programming Language :: Python :: 3
Classifier: Programming Language :: Python :: 3.6
Classifier: Programming Language :: Python :: 3.7
Classifier: Programming Language :: Python :: 3.8
Classifier: License :: OSI Approved :: MIT License
Requires-Dist: tqdm
Requires-Dist: paramtools
Requires-Dist: pandas
